{
  "Projects": [
    {
      "GlobalData": {
        "ProjectId": "41120b41-1856-4456-8254-95ee5f7d0d14",
        "ProjectName": "projectALotOfDatabase",
        "DBTypeName": "SQL Server",
        "Environments": null,
        "SourceControlPathType": 0,
        "Configuration": {
          "BuildMigrationScriptAutomatically": true,
          "BuildMethod": 0,
          "NumberOfRevisionsInViewHistory": 10,
          "NumberOfTagsInBuildOptions": 10,
          "BuildDeploymentScriptOnPush": false,
          "PreventCommitObjectWithConflict": false
        },
        "ProjectArchitecture": 0,
        "LocalDirectory": "C:\\Users\\admin\\Documents\\projectName"
      },
      "UserData": [
        {
          "UserName": "KyryloZ-DBM",
          "DatabasesData": []
        }
      ]
    }
  ],
  "GlobalConfigurations": null
}